sentry_telegram/__init__.py
sentry_telegram/plugin.py
sentry_telegram_aputilov-0.4.13.dist-info/LICENSE
sentry_telegram_aputilov-0.4.13.dist-info/METADATA
sentry_telegram_aputilov-0.4.13.dist-info/WHEEL
sentry_telegram_aputilov-0.4.13.dist-info/entry_points.txt
sentry_telegram_aputilov-0.4.13.dist-info/top_level.txt
sentry_telegram_aputilov-0.4.13.dist-info/RECORD
