Metadata-Version: 2.1
Name: sentry-telegram-aputilov
Version: 0.4.13
Summary: Plugin for Sentry which allows sending notification via Telegram messenger.
Home-page: https://github.com/m8rge/sentry-telegram
Author: Viacheslav Butorov
Author-email: butorovv@gmail.com
License: MIT
Platform: UNKNOWN
Classifier: Development Status :: 5 - Production/Stable
Classifier: Environment :: Console
Classifier: Intended Audience :: Developers
Classifier: Intended Audience :: System Administrators
Classifier: License :: OSI Approved :: MIT License
Classifier: Operating System :: OS Independent
Classifier: Programming Language :: Python
Classifier: Programming Language :: Python :: 2.7
Classifier: Programming Language :: Python :: Implementation :: CPython
Classifier: Topic :: Software Development :: Bug Tracking
Classifier: Topic :: Software Development :: Quality Assurance
Classifier: Topic :: System :: Monitoring
